Workbook

Sheet 预算摘要
A1: 一台同步辐射加速器 + 十条光束线智能监控与调优预算
A4: 口径 | B4: 3年建设期，2026年名义含税人民币；复用既有EPICS/PSS/EPS/PLC和机房；金额单位：万元。
A5: 不重复列支 | B5: 硬件仅为采购；算力为租赁；外部软件仅为第三方许可；自主开发、系统搭建、集成、调试和建设期运维全部归入人力。
A6: 决策提示 | B6: L1适合先立项；L2需十线逐条冻结动作/诊断清单后批复；L3建议分门禁拨款并预留后续2年运行成熟期。
A9: 版本 | B9: 定位摘要 | C9: 硬件采购 | D9: 算力租赁 | E9: 外部软件 | F9: 人力成本 | G9: 不可预见费 | H9: 基准总额 | I9: 折合亿元 | J9: 低位情景 | K9: 高位情景 | L9: 建成后年运行费（估算）
A10: L1 | B10: 全设施状态底座；十线给方法，1–2线实机辅助调优 | C10: =L1明细!M8 -> 634 | D10: =L1明细!M9 -> 276 | E10: =L1明细!M10 -> 150 | F10: =L1明细!M11 -> 1290.2 | G10: =L1明细!H30 -> 352.53 | H10: =L1明细!H31 -> 2702.73 | I10: =H10/10000 -> 0.270273 | J10: =(C10*假设与口径!$D$17+D10*假设与口径!$D$18+E10*假设与口径!$D$19+F10*假设与口径!$D$20)*(1+假设与口径!$C$12) -> 2095.8405 | K10: =(C10*假设与口径!$E$17+D10*假设与口径!$E$18+E10*假设与口径!$E$19+F10*假设与口径!$E$20)*(1+假设与口径!$C$12) -> 3537.3425 | L10: =C10*5%+D10/假设与口径!$C$8+E10/假设与口径!$C$8+人力模型!$F$25 -> 372.3
A11: L2 | B11: 加速器自动监测；十线多参数、多目标闭环自主调优 | C11: =L2明细!M8 -> 1965 | D11: =L2明细!M9 -> 984 | E11: =L2明细!M10 -> 450 | F11: =L2明细!M11 -> 2649 | G11: =L2明细!H32 -> 907.2 | H11: =L2明细!H33 -> 6955.2 | I11: =H11/10000 -> 0.69552 | J11: =(C11*假设与口径!$D$17+D11*假设与口径!$D$18+E11*假设与口径!$D$19+F11*假设与口径!$D$20)*(1+假设与口径!$C$21) -> 5278.6725 | K11: =(C11*假设与口径!$E$17+D11*假设与口径!$E$18+E11*假设与口径!$E$19+F11*假设与口径!$E$20)*(1+假设与口径!$C$21) -> 9219.2625 | L11: =C11*5%+D11/假设与口径!$C$8+E11/假设与口径!$C$8+人力模型!$F$26 -> 960.45
A12: L3 | B12: 预测诊断；十线与加速器同步调控，接近限定边界全自主 | C12: =L3明细!M8 -> 4300 | D12: =L3明细!M9 -> 2802 | E12: =L3明细!M10 -> 900 | F12: =L3明细!M11 -> 4023.6 | G12: =L3明细!H35 -> 2405.12 | H12: =L3明细!H36 -> 14430.72 | I12: =H12/10000 -> 1.443072 | J12: =(C12*假设与口径!$D$17+D12*假设与口径!$D$18+E12*假设与口径!$D$19+F12*假设与口径!$D$20)*(1+假设与口径!$C$22) -> 10777.872 | K12: =(C12*假设与口径!$E$17+D12*假设与口径!$E$18+E12*假设与口径!$E$19+F12*假设与口径!$E$20)*(1+假设与口径!$C$22) -> 19407 | L12: =C12*5%+D12/假设与口径!$C$8+E12/假设与口径!$C$8+人力模型!$F$27 -> 2137.4
A15: 结论 | B15: 建议把L1作为可独立验收的一期；L2、L3按G1 Shadow→G2监督执行→G3模块闭环→G4多线运行→G5限定无人值守分段拨款。

Sheet 假设与口径
A1: 预算模型假设与编制口径
A4: 编辑说明 | B4: 黄色底、蓝色字体为可编辑输入；黑色为公式。金额单位均为万元人民币。
A5: 模型边界 | B5: 3年建设期、2026年名义含税估算；复用现有EPICS/PSS/EPS/PLC及既有机房，只计增量建设。
A7: 假设ID | B7: 参数 | C7: 基准值 | D7: 低位系数 | E7: 高位系数 | F7: 单位 | G7: 说明/来源
A8: A-001 | B8: 建设期 | C8: 3 | F8: 年 | G8: 统一按3年比较；L3成熟运行通常仍需后续2年。
A9: A-002 | B9: 预算汇率 | C9: 7 | F9: CNY/USD | G9: SAFE 2026-08-18中间价6.7905；预算采用7.00留出结算与波动余量。
A10: A-003 | B10: 价格口径 | C10: 1 | F10: 含税名义价 | G10: 最终以国内可采购云、专线和设备供应商含税报价替换。
A11: A-004 | B11: 既有资产复用 | C11: 1 | F11: 是 | G11: 不重复购买现有控制系统、安全联锁、设备PLC和基础机房。
A12: A-005 | B12: L1不可预见费率 | C12: 0.15 | F12: % | G12: 覆盖接口不一致、现场改造和供应商报价波动。
A13: A-006 | B13: H100等效租赁单价 | C13: 45 | F13: 元/GPU·h | G13: 基于公开长期/预留价格约33元/GPU·h，加税费、区域和服务形态余量。
A14: A-007 | B14: 小模型GPU租赁单价 | C14: 15 | F14: 元/GPU·h | G14: A100/L4/L40S等效混合口径；需以国内资源池报价替换。
A15: A-008 | B15: 人年综合成本 | C15: 1 | F15: 见人力模型 | G15: 团队制核算：实验室老师/工程师40万元/年，算法总开发50万元/年，学生0.4万元/月；来源为用户本轮提供。
A16: A-009 | B16: 安全架构 | C16: 1 | F16: 分层控制 | G16: Actor LLM只提出方案；Verifier不是安全联锁；动作必须经确定性Plan和PSS/EPS/PLC。
A17: A-010 | B17: 硬件敏感性 | C17: 1 | D17: 0.7 | E17: 1.3 | F17: 倍 | G17: 低位=高复用；高位=新增诊断、冗余和控制网改造较多。
A18: A-011 | B18: 算力敏感性 | C18: 1 | D18: 0.75 | E18: 1.5 | F18: 倍 | G18: 受国内GPU供应、预留折扣、仿真CPU量和专线影响。
A19: A-012 | B19: 外部软件敏感性 | C19: 1 | D19: 0.5 | E19: 1.5 | F19: 倍 | G19: 开源优先可降低；商业多物理、数据库和企业AI运行时会提高。
A20: A-013 | B20: 人力敏感性 | C20: 1 | D20: 0.85 | E20: 1.25 | F20: 倍 | G20: 受十条线站异构程度、驻场年限、验证强度和既有团队可用性影响。
A21: A-014 | B21: L2不可预见费率 | C21: 0.15 | F21: % | G21: 十线闭环存在集成和验收不确定性。
A22: A-015 | B22: L3不可预见费率 | C22: 0.2 | F22: % | G22: 加速器协同调控与设施级自主运行风险更高。
A23: A-016 | B23: 实验室老师/开发工程师年成本 | C23: 40 | F23: 万元/人年 | G23: 用户给定：实验室老师和代码/算法工程师均按40万元/年。
A24: A-017 | B24: 算法总开发师年成本 | C24: 50 | F24: 万元/人年 | G24: 用户给定：算法总开发师按50万元/年。
A25: A-018 | B25: 学生月成本 | C25: 0.4 | F25: 万元/人月 | G25: 用户给定：学生4000元/月，即0.4万元/月。
A26: A-019 | B26: 学生年成本 | C26: =C25*12 -> 4.8 | F26: 万元/人年 | G26: 由学生月成本乘12个月自动计算。

Sheet 算力模型
A1: 算力租赁模型（不含运维人力）
A4: 价格锚点
A5: 指标 | B5: 低/基准 | C5: 高 | D5: 单位 | E5: 来源/说明
A6: AWS H100容量块低/高 | B6: 3.933 | C6: 4.72 | D6: USD/GPU·h | E6: S-001；动态容量价
A7: Google 8×H100按需 | B7: 88.49 | D7: USD/实例·h | E7: S-002；约11.06 USD/GPU·h
A8: Google 8×H100三年承诺 | B8: 38.864 | D8: USD/实例·h | E8: S-002；约4.86 USD/GPU·h
A9: SAFE中间价 | B9: 6.7905 | D9: CNY/USD | E9: S-003；2026-08-18
A10: 预算汇率 | B10: =假设与口径!$C$9 -> 7 | D10: CNY/USD | E10: A-002
A11: 预算H100单价 | B11: =假设与口径!$C$13/10000 -> 0.0045 | D11: 万元/GPU·h | E11: A-006
A12: 预算小模型GPU单价 | B12: =假设与口径!$C$14/10000 -> 0.0015 | D12: 万元/GPU·h | E12: A-007
A15: 版本算力用量
A16: 版本 | B16: 小模型GPU·h/年 | C16: H100等效GPU·h/年 | D16: CPU/HPC（万元/年） | E16: 存储/专线（万元/年） | F16: 峰值/容灾（万元/年） | G16: 年度合计（万元） | H16: 建设期（年） | I16: 三年合计（万元） | J16: 说明
A17: L1 | B17: 8000 | C17: 0 | D17: 40 | E17: 40 | F17: 0 | G17: =B17*$B$12+C17*$B$11+D17+E17+F17 -> 92 | H17: =假设与口径!$C$8 -> 3 | I17: =G17*H17 -> 276 | J17: 小模型训练/推理；仿真以CPU为主。
A18: L2 | B18: 24000 | C18: 16000 | D18: 120 | E18: 100 | F18: 0 | G18: =B18*$B$12+C18*$B$11+D18+E18+F18 -> 328 | H18: =假设与口径!$C$8 -> 3 | I18: =G18*H18 -> 984 | J18: 8卡大模型阶段性适配，4卡等效在线评估。
A19: L3 | B19: 56000 | C19: 40000 | D19: 300 | E19: 220 | F19: 150 | G19: =B19*$B$12+C19*$B$11+D19+E19+F19 -> 934 | H19: =假设与口径!$C$8 -> 3 | I19: =G19*H19 -> 2802 | J19: 双8卡适配、持续评估、全设施物理仿真和容灾峰值。

Sheet 人力模型
A1: 人力成本模型（实验室老师/工程师带学生的团队制口径）
A4: 不重复列支规则 | B4: 每条光束线由1名实验室老师、1名代码工程师带4–6名学生；全设施共享1名算法总开发师、1–2名算法工程师和2–3名学生。学生按0.4万元/月计。自主开发、集成、调试和建设期运维不再另列。
A6: 角色 | B6: 综合成本（万元/人年） | C6: L1人年 | D6: L2人年 | E6: L3人年 | F6: L1成本 | G6: L2成本 | H6: L3成本 | I6: 职责边界
A7: 光束线实验室老师 | B7: =假设与口径!$C$23 -> 40 | C7: =$B$19*$C$19 -> 10 | D7: =$B$20*$C$20 -> 20 | E7: =$B$21*$C$21 -> 30 | F7: =B7*C7 -> 400 | G7: =B7*D7 -> 800 | H7: =B7*E7 -> 1200 | I7: 每线物理任务、数据定义、现场验证和验收
A8: 光束线代码开发工程师 | B8: =假设与口径!$C$23 -> 40 | C8: =$B$19*$C$19 -> 10 | D8: =$B$20*$C$20 -> 20 | E8: =$B$21*$C$21 -> 30 | F8: =B8*C8 -> 400 | G8: =B8*D8 -> 800 | H8: =B8*E8 -> 1200 | I8: 每线数字孪生、数据接入、控制适配和联调
A9: 光束线学生 | B9: =假设与口径!$C$26 -> 4.8 | C9: =$B$19*$C$19*$D$19 -> 40 | D9: =$B$20*$C$20*$D$20 -> 100 | E9: =$B$21*$C$21*$D$21 -> 180 | F9: =B9*C9 -> 192 | G9: =B9*D9 -> 480 | H9: =B9*E9 -> 864 | I9: 数据整理、建模、测试、实验记录和工具开发
A10: 加速器老师+代码工程师 | B10: =假设与口径!$C$23 -> 40 | C10: =2*$E$19 -> 3 | D10: =2*$E$20 -> 4 | E10: =2*$E$21 -> 6 | F10: =B10*C10 -> 120 | G10: =B10*D10 -> 160 | H10: =B10*E10 -> 240 | I10: 加速器在线监测、模型、接口及L3协同调控；人数按两类人员合计
A11: 加速器学生 | B11: =假设与口径!$C$26 -> 4.8 | C11: =$E$19*$D$19 -> 6 | D11: =$E$20*$D$20 -> 10 | E11: =$E$21*$D$21 -> 18 | F11: =B11*C11 -> 28.8 | G11: =B11*D11 -> 48 | H11: =B11*E11 -> 86.4 | I11: 状态数据、异常样本、模型测试和现场验证
A12: 算法总开发师 | B12: =假设与口径!$C$24 -> 50 | C12: =$F$19 -> 1.5 | D12: =$F$20 -> 2.5 | E12: =$F$21 -> 3 | F12: =B12*C12 -> 75 | G12: =B12*D12 -> 125 | H12: =B12*E12 -> 150 | I12: Simulator–Verifier–Actor总体算法和技术决策
A13: 共享算法工程师 | B13: =假设与口径!$C$23 -> 40 | C13: =$F$19*$G$19 -> 1.5 | D13: =$F$20*$G$20 -> 5 | E13: =$F$21*$G$21 -> 6 | F13: =B13*C13 -> 60 | G13: =B13*D13 -> 200 | H13: =B13*E13 -> 240 | I13: 代理模型、优化、评估、MLOps和工具链
A14: 共享算法学生 | B14: =假设与口径!$C$26 -> 4.8 | C14: =$F$19*$H$19 -> 3 | D14: =$F$20*$H$20 -> 7.5 | E14: =$F$21*$H$21 -> 9 | F14: =B14*C14 -> 14.4 | G14: =B14*D14 -> 36 | H14: =B14*E14 -> 43.2 | I14: 样本构造、训练评估、回放及实验支持
A15: 合计 | C15: =SUM(C7:C14) -> 75 | D15: =SUM(D7:D14) -> 169 | E15: =SUM(E7:E14) -> 282 | F15: =SUM(F7:F14) -> 1290.2 | G15: =SUM(G7:G14) -> 2649 | H15: =SUM(H7:H14) -> 4023.6 | I15: 学生人年纳入工作量统计，但按4.8万元/人年计费。
A17: 建设期团队投入假设（黄色单元格可调整）
A18: 版本 | B18: 光束线数量 | C18: 每线团队年 | D18: 每团队学生数 | E18: 加速器团队年 | F18: 共享算法团队年 | G18: 算法工程师数 | H18: 算法学生数 | I18: 说明
A19: L1 | B19: 10 | C19: 1 | D19: 4 | E19: 1.5 | F19: 1.5 | G19: 1 | H19: 2 | I19: 十线底座平均1团队年/线；1–2线重点验证；学生取下限4人。
A20: L2 | B20: 10 | C20: 2 | D20: 5 | E20: 2 | F20: 2.5 | G20: 2 | H20: 3 | I20: 十线闭环平均2团队年/线；学生取中值5人。
A21: L3 | B21: 10 | C21: 3 | D21: 6 | E21: 3 | F21: 3 | G21: 2 | H21: 3 | I21: 十线高精度与协同控制平均3团队年/线；学生取上限6人。
A23: 建成后年度运维人力假设（不计入三年建设额）
A24: 版本 | B24: 线站团队年/年 | C24: 加速器团队年/年 | D24: 算法团队年/年 | E24: 对应建设期参数行 | F24: 年度人力成本（万元）
A25: L1 | B25: 1 | C25: 0.5 | D25: 0.5 | E25: 19 | F25: =(B25+C25)*(2*$B$7+$D$19*$B$9)+D25*($B$12+$G$19*$B$13+$H$19*$B$14) -> 198.6
A26: L2 | B26: 2.5 | C26: 0.5 | D26: 0.5 | E26: 20 | F26: =(B26+C26)*(2*$B$7+$D$20*$B$9)+D26*($B$12+$G$20*$B$13+$H$20*$B$14) -> 384.2
A27: L3 | B27: 4 | C27: 1 | D27: 1 | E27: 21 | F27: =(B27+C27)*(2*$B$7+$D$21*$B$9)+D27*($B$12+$G$21*$B$13+$H$21*$B$14) -> 688.4

Sheet L1明细
A1: L1版本预算明细
A4: 版本定位 | B4: 数字孪生和状态感知覆盖加速器与十线；加速器在线检测；十线给出调优方法，重点在1–2线测试并提供辅助指导。
A5: 编制规则 | B5: 硬件仅列采购；算力优先租赁；外部软件单列；系统搭建、开发、集成、调试和运维均归人力。
A7: 序号 | B7: 费用类别 | C7: 子项 | D7: 单位 | E7: 数量 | F7: 单价（万元） | G7: 年限 | H7: 小计（万元） | I7: 口径/说明 | J7: 假设ID | L7: 类别汇总 | M7: 金额（万元）
A8: 1 | B8: 硬件采购 | C8: 边缘采集与工业网关 | D8: 套 | E8: 12 | F8: 12 | G8: 1 | H8: =E8*F8*G8 -> 144 | I8: 一台加速器、十条线和一套中心冗余 | J8: A-004 | L8: 硬件采购 | M8: =SUMIF($B$8:$B$27,L8,$H$8:$H$27) -> 634
A9: 2 | B9: 硬件采购 | C9: 增量诊断传感与DAQ | D9: 设施/线站 | E9: 11 | F9: 20 | G9: 1 | H9: =E9*F9*G9 -> 220 | I9: 状态底座覆盖全设施，重点改造1–2条试点线 | J9: A-004 | L9: 算力租赁 | M9: =SUMIF($B$8:$B$27,L9,$H$8:$H$27) -> 276
A10: 3 | B10: 硬件采购 | C10: 时序存储、热缓存与备份 | D10: 套 | E10: 1 | F10: 110 | G10: 1 | H10: =E10*F10*G10 -> 110 | I10: 只计采购，不含部署运维 | J10: A-004 | L10: 外部软件 | M10: =SUMIF($B$8:$B$27,L10,$H$8:$H$27) -> 150
A11: 4 | B11: 硬件采购 | C11: 控制网隔离、时间同步与安全设备 | D11: 套 | E11: 1 | F11: 80 | G11: 1 | H11: =E11*F11*G11 -> 80 | I11: 不替换既有PSS/EPS | J11: A-009 | L11: 人力成本 | M11: =SUMIF($B$8:$B$27,L11,$H$8:$H$27) -> 1290.2
A12: 5 | B12: 硬件采购 | C12: test IOC/HIL试验台 | D12: 套 | E12: 2 | F12: 40 | G12: 1 | H12: =E12*F12*G12 -> 80 | I12: 对应1–2条实机验证线 | J12: A-009
A13: 6 | B13: 算力租赁 | C13: 小模型GPU租赁 | D13: GPU·h/年 | E13: =算力模型!B17 -> 8000 | F13: =算力模型!$B$12 -> 0.0015 | G13: =算力模型!H17 -> 3 | H13: =E13*F13*G13 -> 36 | I13: 不含云运维人力 | J13: A-007
A14: 7 | B14: 算力租赁 | C14: CPU/HPC物理仿真租赁 | D14: 年 | E14: 1 | F14: =算力模型!D17 -> 40 | G14: =算力模型!H17 -> 3 | H14: =E14*F14*G14 -> 120 | I14: Simulator批量仿真 | J14: A-001
A15: 8 | B15: 算力租赁 | C15: 云存储、专线与备份租赁 | D15: 年 | E15: 1 | F15: =算力模型!E17 -> 40 | G15: =算力模型!H17 -> 3 | H15: =E15*F15*G15 -> 120 | I15: 基础设施租赁，不含服务人员 | J15: A-001
A16: 9 | B16: 外部软件 | C16: 商业物理/光学求解器预留 | D16: 项 | E16: 1 | F16: 50 | G16: 1 | H16: =E16*F16*G16 -> 50 | I16: 开源工具不足时采购 | J16: A-012
A17: 10 | B17: 外部软件 | C17: 商业数据库/可观测性订阅 | D17: 项 | E17: 1 | F17: 30 | G17: 1 | H17: =E17*F17*G17 -> 30 | I17: 只列外购许可 | J17: A-012
A18: 11 | B18: 外部软件 | C18: 企业AI运行时许可预留 | D18: 项 | E18: 1 | F18: 30 | G18: 1 | H18: =E18*F18*G18 -> 30 | I18: 生产部署可选；研究开发可用开源 | J18: A-012
A19: 12 | B19: 外部软件 | C19: 安全扫描/备份软件许可 | D19: 项 | E19: 1 | F19: 40 | G19: 1 | H19: =E19*F19*G19 -> 40 | I19: 不含实施服务 | J19: A-012
A20: 13 | B20: 人力成本 | C20: 光束线实验室老师 | D20: 人年 | E20: =人力模型!C7 -> 10 | F20: =人力模型!$B$7 -> 40 | G20: 1 | H20: =E20*F20*G20 -> 400 | I20: 每线物理任务、数据定义、现场验证和验收 | J20: A-008
A21: 14 | B21: 人力成本 | C21: 光束线代码开发工程师 | D21: 人年 | E21: =人力模型!C8 -> 10 | F21: =人力模型!$B$8 -> 40 | G21: 1 | H21: =E21*F21*G21 -> 400 | I21: 每线数字孪生、数据接入、控制适配和联调 | J21: A-008
A22: 15 | B22: 人力成本 | C22: 光束线学生 | D22: 人年 | E22: =人力模型!C9 -> 40 | F22: =人力模型!$B$9 -> 4.8 | G22: 1 | H22: =E22*F22*G22 -> 192 | I22: 数据整理、建模、测试、实验记录和工具开发 | J22: A-008
A23: 16 | B23: 人力成本 | C23: 加速器老师+代码工程师 | D23: 人年 | E23: =人力模型!C10 -> 3 | F23: =人力模型!$B$10 -> 40 | G23: 1 | H23: =E23*F23*G23 -> 120 | I23: 加速器在线监测、模型、接口及L3协同调控；人数按两类人员合计 | J23: A-008
A24: 17 | B24: 人力成本 | C24: 加速器学生 | D24: 人年 | E24: =人力模型!C11 -> 6 | F24: =人力模型!$B$11 -> 4.8 | G24: 1 | H24: =E24*F24*G24 -> 28.8 | I24: 状态数据、异常样本、模型测试和现场验证 | J24: A-008
A25: 18 | B25: 人力成本 | C25: 算法总开发师 | D25: 人年 | E25: =人力模型!C12 -> 1.5 | F25: =人力模型!$B$12 -> 50 | G25: 1 | H25: =E25*F25*G25 -> 75 | I25: Simulator–Verifier–Actor总体算法和技术决策 | J25: A-008
A26: 19 | B26: 人力成本 | C26: 共享算法工程师 | D26: 人年 | E26: =人力模型!C13 -> 1.5 | F26: =人力模型!$B$13 -> 40 | G26: 1 | H26: =E26*F26*G26 -> 60 | I26: 代理模型、优化、评估、MLOps和工具链 | J26: A-008
A27: 20 | B27: 人力成本 | C27: 共享算法学生 | D27: 人年 | E27: =人力模型!C14 -> 3 | F27: =人力模型!$B$14 -> 4.8 | G27: 1 | H27: =E27*F27*G27 -> 14.4 | I27: 样本构造、训练评估、回放及实验支持 | J27: A-008
G29: 直接费用小计 | H29: =SUM(H8:H27) -> 2350.2
G30: 不可预见费 | H30: =H29*假设与口径!$C$12 -> 352.53
G31: 三年总预算 | H31: =H29+H30 -> 2702.73

Sheet L2明细
A1: L2版本预算明细
A4: 版本定位 | B4: 全设施高精度感知、物理模型和AI代理；加速器自动监测；十线多参数、多目标闭环自主调优。
A5: 编制规则 | B5: 硬件仅列采购；算力优先租赁；外部软件单列；系统搭建、开发、集成、调试和运维均归人力。
A7: 序号 | B7: 费用类别 | C7: 子项 | D7: 单位 | E7: 数量 | F7: 单价（万元） | G7: 年限 | H7: 小计（万元） | I7: 口径/说明 | J7: 假设ID | L7: 类别汇总 | M7: 金额（万元）
A8: 1 | B8: 硬件采购 | C8: 双机边缘采集与工业网关 | D8: 套 | E8: 22 | F8: 15 | G8: 1 | H8: =E8*F8*G8 -> 330 | I8: 加速器和十线关键节点冗余 | J8: A-004 | L8: 硬件采购 | M8: =SUMIF($B$8:$B$29,L8,$H$8:$H$29) -> 1965
A9: 2 | B9: 硬件采购 | C9: 高精度诊断传感与DAQ | D9: 设施/线站 | E9: 11 | F9: 55 | G9: 1 | H9: =E9*F9*G9 -> 605 | I9: 支撑十线多参数闭环 | J9: A-004 | L9: 算力租赁 | M9: =SUMIF($B$8:$B$29,L9,$H$8:$H$29) -> 984
A10: 3 | B10: 硬件采购 | C10: 时序数据热存储集群 | D10: 节点 | E10: 2 | F10: 150 | G10: 1 | H10: =E10*F10*G10 -> 300 | I10: 原始数据仍复用设施数据平台 | J10: A-004 | L10: 外部软件 | M10: =SUMIF($B$8:$B$29,L10,$H$8:$H$29) -> 450
A11: 4 | B11: 硬件采购 | C11: 控制网隔离、时间同步与安全设备 | D11: 套 | E11: 1 | F11: 180 | G11: 1 | H11: =E11*F11*G11 -> 180 | I11: 多线闭环的唯一写通道 | J11: A-009 | L11: 人力成本 | M11: =SUMIF($B$8:$B$29,L11,$H$8:$H$29) -> 2649
A12: 5 | B12: 硬件采购 | C12: 十线HIL/故障注入适配台 | D12: 套 | E12: 10 | F12: 25 | G12: 1 | H12: =E12*F12*G12 -> 250 | I12: 每条线具备回放和故障注入 | J12: A-009
A13: 6 | B13: 硬件采购 | C13: 确定性Plan执行网关 | D13: 套 | E13: 10 | F13: 30 | G13: 1 | H13: =E13*F13*G13 -> 300 | I13: Actor不能直接写PV | J13: A-009
A14: 7 | B14: 算力租赁 | C14: 中型推理GPU租赁 | D14: GPU·h/年 | E14: =算力模型!B18 -> 24000 | F14: =算力模型!$B$12 -> 0.0015 | G14: =算力模型!H18 -> 3 | H14: =E14*F14*G14 -> 108 | I14: 在线评估和代理模型 | J14: A-007
A15: 8 | B15: 算力租赁 | C15: H100等效大模型适配 | D15: GPU·h/年 | E15: =算力模型!C18 -> 16000 | F15: =算力模型!$B$11 -> 0.0045 | G15: =算力模型!H18 -> 3 | H15: =E15*F15*G15 -> 216 | I15: 阶段性8卡适配 | J15: A-006
A16: 9 | B16: 算力租赁 | C16: CPU/HPC物理仿真租赁 | D16: 年 | E16: 1 | F16: =算力模型!D18 -> 120 | G16: =算力模型!H18 -> 3 | H16: =E16*F16*G16 -> 360 | I16: 十线高保真Simulator | J16: A-001
A17: 10 | B17: 算力租赁 | C17: 云存储、专线与备份租赁 | D17: 年 | E17: 1 | F17: =算力模型!E18 -> 100 | G17: =算力模型!H18 -> 3 | H17: =E17*F17*G17 -> 300 | I17: 基础设施租赁，不含运维人力 | J17: A-001
A18: 11 | B18: 外部软件 | C18: 商业多物理/光学求解器 | D18: 项 | E18: 1 | F18: 120 | G18: 1 | H18: =E18*F18*G18 -> 120 | I18: 十线模型适配预留 | J18: A-012
A19: 12 | B19: 外部软件 | C19: 商业时序库/可观测性订阅 | D19: 项 | E19: 1 | F19: 100 | G19: 1 | H19: =E19*F19*G19 -> 100 | I19: 三年许可 | J19: A-012
A20: 13 | B20: 外部软件 | C20: 企业AI运行时许可 | D20: 项 | E20: 1 | F20: 100 | G20: 1 | H20: =E20*F20*G20 -> 100 | I20: 按生产GPU规模预留 | J20: A-012
A21: 14 | B21: 外部软件 | C21: 网络安全与软件测试许可 | D21: 项 | E21: 1 | F21: 130 | G21: 1 | H21: =E21*F21*G21 -> 130 | I21: 只列许可，不列实施服务 | J21: A-012
A22: 15 | B22: 人力成本 | C22: 光束线实验室老师 | D22: 人年 | E22: =人力模型!D7 -> 20 | F22: =人力模型!$B$7 -> 40 | G22: 1 | H22: =E22*F22*G22 -> 800 | I22: 每线物理任务、数据定义、现场验证和验收 | J22: A-008
A23: 16 | B23: 人力成本 | C23: 光束线代码开发工程师 | D23: 人年 | E23: =人力模型!D8 -> 20 | F23: =人力模型!$B$8 -> 40 | G23: 1 | H23: =E23*F23*G23 -> 800 | I23: 每线数字孪生、数据接入、控制适配和联调 | J23: A-008
A24: 17 | B24: 人力成本 | C24: 光束线学生 | D24: 人年 | E24: =人力模型!D9 -> 100 | F24: =人力模型!$B$9 -> 4.8 | G24: 1 | H24: =E24*F24*G24 -> 480 | I24: 数据整理、建模、测试、实验记录和工具开发 | J24: A-008
A25: 18 | B25: 人力成本 | C25: 加速器老师+代码工程师 | D25: 人年 | E25: =人力模型!D10 -> 4 | F25: =人力模型!$B$10 -> 40 | G25: 1 | H25: =E25*F25*G25 -> 160 | I25: 加速器在线监测、模型、接口及L3协同调控；人数按两类人员合计 | J25: A-008
A26: 19 | B26: 人力成本 | C26: 加速器学生 | D26: 人年 | E26: =人力模型!D11 -> 10 | F26: =人力模型!$B$11 -> 4.8 | G26: 1 | H26: =E26*F26*G26 -> 48 | I26: 状态数据、异常样本、模型测试和现场验证 | J26: A-008
A27: 20 | B27: 人力成本 | C27: 算法总开发师 | D27: 人年 | E27: =人力模型!D12 -> 2.5 | F27: =人力模型!$B$12 -> 50 | G27: 1 | H27: =E27*F27*G27 -> 125 | I27: Simulator–Verifier–Actor总体算法和技术决策 | J27: A-008
A28: 21 | B28: 人力成本 | C28: 共享算法工程师 | D28: 人年 | E28: =人力模型!D13 -> 5 | F28: =人力模型!$B$13 -> 40 | G28: 1 | H28: =E28*F28*G28 -> 200 | I28: 代理模型、优化、评估、MLOps和工具链 | J28: A-008
A29: 22 | B29: 人力成本 | C29: 共享算法学生 | D29: 人年 | E29: =人力模型!D14 -> 7.5 | F29: =人力模型!$B$14 -> 4.8 | G29: 1 | H29: =E29*F29*G29 -> 36 | I29: 样本构造、训练评估、回放及实验支持 | J29: A-008
G31: 直接费用小计 | H31: =SUM(H8:H29) -> 6048
G32: 不可预见费 | H32: =H31*假设与口径!$C$21 -> 907.2
G33: 三年总预算 | H33: =H31+H32 -> 6955.2

Sheet L3明细
A1: L3版本预算明细
A4: 版本定位 | B4: 全状态感知、预测诊断和自主优化；光束线与加速器同步调控，形成限定边界内接近完全自主运行的设施能力。
A5: 编制规则 | B5: 硬件仅列采购；算力优先租赁；外部软件单列；系统搭建、开发、集成、调试和运维均归人力。
A7: 序号 | B7: 费用类别 | C7: 子项 | D7: 单位 | E7: 数量 | F7: 单价（万元） | G7: 年限 | H7: 小计（万元） | I7: 口径/说明 | J7: 假设ID | L7: 类别汇总 | M7: 金额（万元）
A8: 1 | B8: 硬件采购 | C8: 双机实时边缘计算与采集节点 | D8: 套 | E8: 22 | F8: 25 | G8: 1 | H8: =E8*F8*G8 -> 550 | I8: 设施级冗余与边缘特征提取 | J8: A-004 | L8: 硬件采购 | M8: =SUMIF($B$8:$B$32,L8,$H$8:$H$32) -> 4300
A9: 2 | B9: 硬件采购 | C9: 全状态高精度诊断传感与DAQ | D9: 设施/线站 | E9: 11 | F9: 100 | G9: 1 | H9: =E9*F9*G9 -> 1100 | I9: 含预测诊断所需增量测点 | J9: A-004 | L9: 算力租赁 | M9: =SUMIF($B$8:$B$32,L9,$H$8:$H$32) -> 2802
A10: 3 | B10: 硬件采购 | C10: 高可用时序存储与热缓存 | D10: 节点 | E10: 2 | F10: 300 | G10: 1 | H10: =E10*F10*G10 -> 600 | I10: 双活/容灾，不重复建设原始数据中心 | J10: A-004 | L10: 外部软件 | M10: =SUMIF($B$8:$B$32,L10,$H$8:$H$32) -> 900
A11: 4 | B11: 硬件采购 | C11: 控制网隔离、时间同步、网络与灾备 | D11: 套 | E11: 1 | F11: 400 | G11: 1 | H11: =E11*F11*G11 -> 400 | I11: 设施级安全域和审计 | J11: A-009 | L11: 人力成本 | M11: =SUMIF($B$8:$B$32,L11,$H$8:$H$32) -> 4023.6
A12: 5 | B12: 硬件采购 | C12: 全设施HIL/故障注入试验台 | D12: 套 | E12: 11 | F12: 50 | G12: 1 | H12: =E12*F12*G12 -> 550 | I12: 加速器与十线联合回放 | J12: A-009
A13: 6 | B13: 硬件采购 | C13: 加速器同步调控安全网关 | D13: 套 | E13: 1 | F13: 600 | G13: 1 | H13: =E13*F13*G13 -> 600 | I13: 不改写PSS/EPS职责 | J13: A-009
A14: 7 | B14: 硬件采购 | C14: 十线确定性执行与回退网关 | D14: 套 | E14: 10 | F14: 50 | G14: 1 | H14: =E14*F14*G14 -> 500 | I14: 白名单动作、签名Plan和安全停止 | J14: A-009
A15: 8 | B15: 算力租赁 | C15: 中型推理GPU租赁 | D15: GPU·h/年 | E15: =算力模型!B19 -> 56000 | F15: =算力模型!$B$12 -> 0.0015 | G15: =算力模型!H19 -> 3 | H15: =E15*F15*G15 -> 252 | I15: 代理模型、在线评估和冗余推理 | J15: A-007
A16: 9 | B16: 算力租赁 | C16: H100等效大模型适配 | D16: GPU·h/年 | E16: =算力模型!C19 -> 40000 | F16: =算力模型!$B$11 -> 0.0045 | G16: =算力模型!H19 -> 3 | H16: =E16*F16*G16 -> 540 | I16: 双8卡阶段性适配 | J16: A-006
A17: 10 | B17: 算力租赁 | C17: CPU/HPC物理仿真租赁 | D17: 年 | E17: 1 | F17: =算力模型!D19 -> 300 | G17: =算力模型!H19 -> 3 | H17: =E17*F17*G17 -> 900 | I17: 加速器—十线联合Simulator | J17: A-001
A18: 11 | B18: 算力租赁 | C18: 云存储、专线与备份租赁 | D18: 年 | E18: 1 | F18: =算力模型!E19 -> 220 | G18: =算力模型!H19 -> 3 | H18: =E18*F18*G18 -> 660 | I18: 基础设施租赁，不含运维人力 | J18: A-001
A19: 12 | B19: 算力租赁 | C19: 峰值与容灾算力预留 | D19: 年 | E19: 1 | F19: =算力模型!F19 -> 150 | G19: =算力模型!H19 -> 3 | H19: =E19*F19*G19 -> 450 | I19: 上线前验证、故障演练和突发适配 | J19: A-011
A20: 13 | B20: 外部软件 | C20: 商业多物理/光学求解器 | D20: 项 | E20: 1 | F20: 250 | G20: 1 | H20: =E20*F20*G20 -> 250 | I20: 加速器—光束线联合模型 | J20: A-012
A21: 14 | B21: 外部软件 | C21: 企业数据治理/时序库订阅 | D21: 项 | E21: 1 | F21: 180 | G21: 1 | H21: =E21*F21*G21 -> 180 | I21: 三年许可 | J21: A-012
A22: 15 | B22: 外部软件 | C22: 企业AI运行时许可 | D22: 项 | E22: 1 | F22: 180 | G22: 1 | H22: =E22*F22*G22 -> 180 | I22: 生产级安全更新和支持预留 | J22: A-012
A23: 16 | B23: 外部软件 | C23: 网络安全/验证软件许可 | D23: 项 | E23: 1 | F23: 150 | G23: 1 | H23: =E23*F23*G23 -> 150 | I23: 只列外购许可 | J23: A-012
A24: 17 | B24: 外部软件 | C24: 标准化建模和测试工具许可 | D24: 项 | E24: 1 | F24: 140 | G24: 1 | H24: =E24*F24*G24 -> 140 | I24: 外购工具预留 | J24: A-012
A25: 18 | B25: 人力成本 | C25: 光束线实验室老师 | D25: 人年 | E25: =人力模型!E7 -> 30 | F25: =人力模型!$B$7 -> 40 | G25: 1 | H25: =E25*F25*G25 -> 1200 | I25: 每线物理任务、数据定义、现场验证和验收 | J25: A-008
A26: 19 | B26: 人力成本 | C26: 光束线代码开发工程师 | D26: 人年 | E26: =人力模型!E8 -> 30 | F26: =人力模型!$B$8 -> 40 | G26: 1 | H26: =E26*F26*G26 -> 1200 | I26: 每线数字孪生、数据接入、控制适配和联调 | J26: A-008
A27: 20 | B27: 人力成本 | C27: 光束线学生 | D27: 人年 | E27: =人力模型!E9 -> 180 | F27: =人力模型!$B$9 -> 4.8 | G27: 1 | H27: =E27*F27*G27 -> 864 | I27: 数据整理、建模、测试、实验记录和工具开发 | J27: A-008
A28: 21 | B28: 人力成本 | C28: 加速器老师+代码工程师 | D28: 人年 | E28: =人力模型!E10 -> 6 | F28: =人力模型!$B$10 -> 40 | G28: 1 | H28: =E28*F28*G28 -> 240 | I28: 加速器在线监测、模型、接口及L3协同调控；人数按两类人员合计 | J28: A-008
A29: 22 | B29: 人力成本 | C29: 加速器学生 | D29: 人年 | E29: =人力模型!E11 -> 18 | F29: =人力模型!$B$11 -> 4.8 | G29: 1 | H29: =E29*F29*G29 -> 86.4 | I29: 状态数据、异常样本、模型测试和现场验证 | J29: A-008
A30: 23 | B30: 人力成本 | C30: 算法总开发师 | D30: 人年 | E30: =人力模型!E12 -> 3 | F30: =人力模型!$B$12 -> 50 | G30: 1 | H30: =E30*F30*G30 -> 150 | I30: Simulator–Verifier–Actor总体算法和技术决策 | J30: A-008
A31: 24 | B31: 人力成本 | C31: 共享算法工程师 | D31: 人年 | E31: =人力模型!E13 -> 6 | F31: =人力模型!$B$13 -> 40 | G31: 1 | H31: =E31*F31*G31 -> 240 | I31: 代理模型、优化、评估、MLOps和工具链 | J31: A-008
A32: 25 | B32: 人力成本 | C32: 共享算法学生 | D32: 人年 | E32: =人力模型!E14 -> 9 | F32: =人力模型!$B$14 -> 4.8 | G32: 1 | H32: =E32*F32*G32 -> 43.2 | I32: 样本构造、训练评估、回放及实验支持 | J32: A-008
G34: 直接费用小计 | H34: =SUM(H8:H32) -> 12025.6
G35: 不可预见费 | H35: =H34*假设与口径!$C$22 -> 2405.12
G36: 三年总预算 | H36: =H34+H35 -> 14430.72

Sheet 版本差异
A1: L1–L3能力边界与Actor闭环定位
A5: 维度 | B5: L1 | C5: L2 | D5: L3 | E5: 预算边界/验收提醒
A6: 覆盖范围 | B6: 一台加速器+十线状态底座；1–2线实机测试 | C6: 一台加速器自动监测；十线闭环调优 | D6: 一台加速器+十线联合状态、诊断和调控 | E6: 不是十套孤立系统
A7: Simulator | B7: 中等精度；历史Flux残差校准 | C7: 十线高精度模型+AI代理 | D7: 加速器—十线联合多速率孪生 | E7: 每条线必须有独立校准和失效域
A8: Verifier | B8: 评分和硬约束检查；辅助决策 | C8: 多目标评分、OOD和回退；闭环门控 | D8: 预测风险、跨子系统约束和容灾验证 | E8: Verifier不能替代PSS/EPS/PLC
A9: Actor LLM | B9: 小模型；直接建议或少轮验证 | C9: 大模型适配；十线多轮工具调用 | D9: 大模型+代理模型；设施级任务编排 | E9: 无任意PV、脚本或联锁修改权
A10: 加速器能力 | B10: 在线检测、报警和人工处置建议 | C10: 自动监测、预测预警；不自动调源 | D10: 经白名单Plan同步调控光源与线站 | E10: 快反馈仍由FPGA/PID/PLC承担
A11: 光束线能力 | B11: 十线给方法；1–2线辅助调优验证 | C11: 十线多参数、多目标闭环自主调优 | D11: 十线协同调优、预测诊断与自主恢复 | E11: 必须按线冻结动作、约束和验收集
A12: 运行成熟度 | B12: Shadow/专家批准 | C12: 多线监督式自主运行 | D12: 限定边界内接近完全自主 | E12: L3不等于取消值班和科研签字
A13: 主验收量 | B13: 覆盖率、检测率、建议接受率、试点效果 | C13: 十线成功率、调优时间、人工接管率、零越权 | D13: 设施可用率、预测提前量、联合恢复率、灾备 | E13: 高危事件按零容忍门禁

Sheet 来源
A1: 证据来源与使用限制（检索截止2026-08-19）
A5: 来源ID | B5: 来源 | C5: 发布者 | D5: 日期 | E5: 关键值/用途 | F5: URL/本地路径 | G5: 限制
A6: S-001 | B6: EC2 Capacity Blocks for ML Pricing | C6: AWS | D6: 2026-07-07有效价 | E6: H100容量块约3.933–4.72 USD/GPU·h | F6: https://aws.amazon.com/ec2/capacityblocks/pricing/ | G6: 动态价格；非中国含税价
A7: S-002 | B7: Accelerator-optimized VM Pricing | C7: Google Cloud | D7: 检索2026-08-19 | E7: 8×H100按需约88.49 USD/h；三年约38.86 USD/h | F7: https://cloud.google.com/products/compute/pricing/accelerator-optimized | G7: 不含磁盘、网络和税
A8: S-003 | B8: 人民币汇率中间价 | C8: SAFE/中国外汇交易中心 | D8: 2026-08-18 | E8: 6.7905 CNY/USD；预算用7.00 | F8: https://www.safe.gov.cn/AppStructured/hlw/RMBQuery.do | G8: 中间价不是结算价
A9: S-004 | B9: NVIDIA NIM FAQ | C9: NVIDIA | D9: 检索2026-08-19 | E9: 生产许可起价4500 USD/GPU·年 | F9: https://docs.api.nvidia.com/nim/docs/product | G9: 起价；最终需询价
A10: S-005 | B10: EPICS Open License | C10: EPICS Collaboration | D10: 检索2026-08-19 | E10: 控制栈可开源复用，降低许可费 | F10: https://epics.anl.gov/license/open.php | G10: 模块许可仍需审计
A11: S-006 | B11: Bluesky Repository | C11: Bluesky Project | D11: 检索2026-08-19 | E11: BSD-3-Clause；实验编排、元数据和中断恢复 | F11: https://github.com/bluesky/bluesky | G11: 开源不等于免集成人力
A12: S-007 | B12: 纳米CT智能化实施路线 | C12: 本地项目文档 | D12: 2026-07 | E12: 安全分层、HIL、门禁和工作包 | F12: ../上海光源纳米CT全流程智能化需求评估与实施路线_2026-07.md | G12: 面向纳米CT，十线需逐条盘点
A13: S-008 | B13: 本次预算需求及团队制用人成本 | C13: 用户 | D13: 2026-08-19 | E13: 一台加速器+十线；L1/L2/L3能力；老师/工程师40万元/年、算法总开发50万元/年、学生0.4万元/月 | F13: 用户需求 | G13: 版本团队年为模型假设，可在“人力模型”黄色单元格调整

Sheet 分年预算
A1: 三年建设资金安排建议
A5: 版本 | B5: 第1年比例 | C5: 第1年金额 | D5: 第2年比例 | E5: 第2年金额 | F5: 第3年比例 | G5: 第3年金额 | H5: 合计
A6: L1 | B6: 0.35 | C6: =预算摘要!$H$10*B6 -> 945.9555 | D6: 0.4 | E6: =预算摘要!$H$10*D6 -> 1081.092 | F6: 0.25 | G6: =预算摘要!$H$10*F6 -> 675.6825 | H6: =SUM(C6,E6,G6) -> 2702.73
A7: L2 | B7: 0.3 | C7: =预算摘要!$H$11*B7 -> 2086.56 | D7: 0.45 | E7: =预算摘要!$H$11*D7 -> 3129.84 | F7: 0.25 | G7: =预算摘要!$H$11*F7 -> 1738.8 | H7: =SUM(C7,E7,G7) -> 6955.2
A8: L3 | B8: 0.25 | C8: =预算摘要!$H$12*B8 -> 3607.68 | D8: 0.4 | E8: =预算摘要!$H$12*D8 -> 5772.288 | F8: 0.35 | G8: =预算摘要!$H$12*F8 -> 5050.752 | H8: =SUM(C8,E8,G8) -> 14430.72
A11: 门禁建议 | B11: 第1年：数据与Shadow；第2年：监督执行和模块闭环；第3年：多线运行。L3的限定无人值守应在三年核心建设后继续以运行成熟项目验收。
